semantix_genai_serve/__init__.py
semantix_genai_serve/huggingface/__init__.py
semantix_genai_serve/huggingface/serve_auto_processor.py
semantix_genai_serve/huggingface/serve_auto_seq2seq_lm.py
semantix_genai_serve/huggingface/serve_auto_tokenizer.py
semantix_genai_serve/semantix_kserve.py
semantix_genai_serve-0.0.5.dist-info/LICENSE.txt
semantix_genai_serve-0.0.5.dist-info/WHEEL
semantix_genai_serve-0.0.5.dist-info/METADATA
semantix_genai_serve-0.0.5.dist-info/RECORD
