Metadata-Version: 2.1
Name: semantix-genai-serve
Version: 0.0.5
Summary: 
Author: Dev Team
Author-email: dev@semantix.ai
Requires-Python: >=3.8,<3.12
Classifier: Programming Language :: Python :: 3
Classifier: Programming Language :: Python :: 3.8
Classifier: Programming Language :: Python :: 3.9
Classifier: Programming Language :: Python :: 3.10
Classifier: Programming Language :: Python :: 3.11
Requires-Dist: bitsandbytes (==0.41.1)
Requires-Dist: kserve (==0.11.0)
Requires-Dist: transformers (>=4.28.0)
